symbolite/abstract/array.py
symbolite/impl/array/default.py
symbolite/impl/array/numpy.py
symbolite/impl/array/sympy.py
symbolite/testsuite/test_array.py
symbolite_array-0.1.dist-info/AUTHORS
symbolite_array-0.1.dist-info/LICENSE
symbolite_array-0.1.dist-info/METADATA
symbolite_array-0.1.dist-info/WHEEL
symbolite_array-0.1.dist-info/top_level.txt
symbolite_array-0.1.dist-info/RECORD
