Metadata-Version: 2.1
Name: symbolite-array
Version: 0.1
Summary: A minimalistic symbolic package.
Author-email: "Hernán E. Grecco" <hernan.grecco@gmail.com>, Mauro Silberberg <maurosilber@gmail.com>
License: MIT License
Project-URL: Homepage, https://github.com/hgrecco/symbolite-array
Project-URL: Bug Tracker, https://github.com/hgrecco/symbolite-array/issues
Keywords: symbolic
Classifier: Programming Language :: Python :: 3
Classifier: License :: OSI Approved :: MIT License
Classifier: Operating System :: OS Independent
Classifier: Intended Audience :: Developers
Classifier: Intended Audience :: Science/Research
Classifier: Topic :: Scientific/Engineering
Classifier: Topic :: Software Development :: Libraries
Requires-Python: >=3.8
License-File: LICENSE
License-File: AUTHORS
Requires-Dist: symbolite (>=0.2)
Provides-Extra: test
Requires-Dist: pytest ; extra == 'test'
